pysmatch/Matcher.py
pysmatch/__init__.py
pysmatch/matching.py
pysmatch/modeling.py
pysmatch/utils.py
pysmatch/visualization.py
pysmatch-2.0.dist-info/licenses/LICENSE
pysmatch-2.0.dist-info/METADATA
pysmatch-2.0.dist-info/WHEEL
pysmatch-2.0.dist-info/top_level.txt
pysmatch-2.0.dist-info/RECORD
