Metadata-Version: 2.4
Name: pysmatch
Version: 2.0
Summary: Propensity Score Matching (PSM) on Python
Home-page: https://github.com/mhcone/pysmatch
Author: Miao HanCheng
Author-email: hanchengmiao@gmail.com
License-File: LICENSE
Requires-Dist: catboost>=1.2.7
Requires-Dist: matplotlib>=3.7.1
Requires-Dist: numpy<2.0.0,>=1.26.4
Requires-Dist: pandas>=2.1.4
Requires-Dist: scipy>=1.13.1
Requires-Dist: seaborn>=0.12.2
Requires-Dist: statsmodels>=0.14.3
Requires-Dist: scikit-learn>=1.5.2
Requires-Dist: imbalanced-learn>=0.12.3
Requires-Dist: optuna>=4.1.0
Dynamic: author
Dynamic: author-email
Dynamic: description
Dynamic: description-content-type
Dynamic: home-page
Dynamic: license-file
Dynamic: requires-dist
Dynamic: summary
